fshasher/__init__.py
fshasher/fshasher.py
fshasher-0.1.0.dist-info/WHEEL
fshasher-0.1.0.dist-info/METADATA
fshasher-0.1.0.dist-info/RECORD
