Metadata-Version: 2.1
Name: fshasher
Version: 0.1.0
Summary: Cross-platform file-object hasher
License: MIT
Author: Matias Grioni
Author-email: matgrioni@gmail.com
Requires-Python: >=3.10,<4.0
Classifier: License :: OSI Approved :: MIT License
Classifier: Programming Language :: Python :: 3
Classifier: Programming Language :: Python :: 3.10
